tests/__init__.py
tests/td_examples.py
tests/utils.py
tests/codecs/__init__.py
tests/codecs/test_json.py
tests/protocols/__init__.py
tests/protocols/conftest.py
tests/protocols/helpers.py
tests/protocols/test_protocols.py
tests/protocols/coap/__init__.py
tests/protocols/coap/conftest.py
tests/protocols/coap/test_client.py
tests/protocols/coap/test_server.py
tests/protocols/http/__init__.py
tests/protocols/http/conftest.py
tests/protocols/http/test_client.py
tests/protocols/http/test_server.py
tests/protocols/mqtt/__init__.py
tests/protocols/mqtt/broker.py
tests/protocols/mqtt/conftest.py
tests/protocols/mqtt/test_client.py
tests/protocols/mqtt/test_server.py
tests/protocols/ws/__init__.py
tests/protocols/ws/conftest.py
tests/protocols/ws/test_client.py
tests/protocols/ws/test_server.py
tests/wot/__init__.py
tests/wot/conftest.py
tests/wot/test_consumed.py
tests/wot/test_dictionaries.py
tests/wot/test_exposed.py
tests/wot/test_servient.py
tests/wot/test_td.py
tests/wot/test_thing.py
tests/wot/test_wot.py
tests/wot/utils.py
tests/wot/discovery/__init__.py
tests/wot/discovery/dnssd/__init__.py
tests/wot/discovery/dnssd/conftest.py
tests/wot/discovery/dnssd/test_service.py
wotpy/__init__.py
wotpy/__version__.py
wotpy/support.py
wotpy/codecs/__init__.py
wotpy/codecs/base.py
wotpy/codecs/enums.py
wotpy/codecs/json_codec.py
wotpy/codecs/text.py
wotpy/protocols/__init__.py
wotpy/protocols/client.py
wotpy/protocols/enums.py
wotpy/protocols/exceptions.py
wotpy/protocols/refs.py
wotpy/protocols/server.py
wotpy/protocols/utils.py
wotpy/protocols/coap/__init__.py
wotpy/protocols/coap/client.py
wotpy/protocols/coap/enums.py
wotpy/protocols/coap/server.py
wotpy/protocols/coap/resources/__init__.py
wotpy/protocols/coap/resources/action.py
wotpy/protocols/coap/resources/event.py
wotpy/protocols/coap/resources/property.py
wotpy/protocols/coap/resources/utils.py
wotpy/protocols/http/__init__.py
wotpy/protocols/http/client.py
wotpy/protocols/http/enums.py
wotpy-0.17.2.dist-info/LICENSE
wotpy-0.17.2.dist-info/METADATA
wotpy-0.17.2.dist-info/WHEEL
wotpy-0.17.2.dist-info/top_level.txt
wotpy-0.17.2.dist-info/RECORD
