Metadata-Version: 2.1
Name: wotpy
Version: 0.17.2
Summary: Python implementation of a W3C WoT Runtime and the WoT Scripting API
Home-page: https://github.com/agmangas/wot-py
Author: Andres Garcia Mangas
Author-email: andres.garcia@fundacionctic.org
Keywords: wot iot gateway fog w3c
Classifier: Development Status :: 4 - Beta
Classifier: Intended Audience :: Developers
Classifier: Natural Language :: English
Classifier: Operating System :: OS Independent
Classifier: License :: OSI Approved :: MIT License
Classifier: Programming Language :: Python :: 3.7
Classifier: Programming Language :: Python :: 3.8
Classifier: Programming Language :: Python :: 3.9
Classifier: Programming Language :: Python :: 3.10
License-File: LICENSE
Requires-Dist: tornado <7.0,>=6.1
Requires-Dist: jsonschema <3.0,>=2.0
Requires-Dist: rx <2.0,>=1.6.0
Requires-Dist: python-slugify <2.0,>=1.2.4
Requires-Dist: aiocoap[all] ==0.4.7
Requires-Dist: aiomqtt <2.0,>=1.2
Requires-Dist: zeroconf <0.37.0,>=0.30.0
Provides-Extra: tests
Requires-Dist: pytest >=6.2.5 ; extra == 'tests'
Requires-Dist: pytest-asyncio ==0.21.1 ; extra == 'tests'
Requires-Dist: pytest-cov <2.6.0,>=2.5.1 ; extra == 'tests'
Requires-Dist: pytest-rerunfailures <11.0,>=10.2 ; extra == 'tests'
Requires-Dist: mock <3.0,>=2.0 ; extra == 'tests'
Requires-Dist: tox <4.0,>=3.0 ; extra == 'tests'
Requires-Dist: faker <14.0.0,>=13.14.0 ; extra == 'tests'
Requires-Dist: Sphinx <2.0.0,>=1.7.5 ; extra == 'tests'
Requires-Dist: sphinx-rtd-theme <0.5.0,>=0.4.0 ; extra == 'tests'
Requires-Dist: pyOpenSSL <19.0.0,>=18.0.0 ; extra == 'tests'
Requires-Dist: coveralls <2.0,>=1.0 ; extra == 'tests'
Requires-Dist: coverage <6.0,>=5.0 ; extra == 'tests'
Requires-Dist: cryptography ==3.4.8 ; extra == 'tests'
Requires-Dist: autopep8 <2.0,>=1.4 ; extra == 'tests'
Requires-Dist: rope <1.0,>=0.14.0 ; extra == 'tests'
Requires-Dist: bump2version <2.0,>=1.0 ; extra == 'tests'
Requires-Dist: coloredlogs ; extra == 'tests'
Requires-Dist: aiozeroconf ==0.1.8 ; extra == 'tests'
Provides-Extra: uvloop
Requires-Dist: uvloop <0.13.0,>=0.12.2 ; extra == 'uvloop'
